.gitignore
LICENSE
README.rst
careful_rm.alias.sh
careful_rm.plugin.zsh
careful_rm.py
setup.cfg
setup.py
careful_rm.egg-info/PKG-INFO
careful_rm.egg-info/SOURCES.txt
careful_rm.egg-info/dependency_links.txt
careful_rm.egg-info/entry_points.txt
careful_rm.egg-info/top_level.txt