Metadata-Version: 1.1
Name: careful-rm
Version: 1.0b10
Summary: A safe wrapper for rm that adds useful warnings and an optional recycle/trash mode
Home-page: https://github.com/MikeDacre/careful_rm
Author: Mike Dacre
Author-email: mike.dacre@gmail.com
License: MIT
Download-URL: https://github.com/MikeDacre/careful_rm/archive/v1.0b10.tar.gz
Keywords: zsh coreutils rm bash shell wrapper trash-mode macos macosx linux command-line oh-my-zsh antigen alternative
Platform: UNKNOWN
Classifier: Development Status :: 4 - Beta
Classifier: Environment :: Console
Classifier: Intended Audience :: End Users/Desktop
Classifier: Intended Audience :: System Administrators
Classifier: License :: OSI Approved :: MIT License
Classifier: Natural Language :: English
Classifier: Operating System :: MacOS :: MacOS X
Classifier: Operating System :: POSIX
Classifier: Programming Language :: Python
Classifier: Programming Language :: Python :: 2
Classifier: Programming Language :: Python :: 3
Classifier: Topic :: Utilities
